CHANGELOG.txt
DOCS.txt
MANIFEST.in
README.md
setup.py
rtorrent/__init__.py
rtorrent/common.py
rtorrent/err.py
rtorrent/file.py
rtorrent/peer.py
rtorrent/torrent.py
rtorrent/tracker.py
rtorrent/lib/__init__.py
rtorrent/lib/bencode.py
rtorrent/lib/torrentparser.py
rtorrent/rpc/__init__.py
rtorrent_python.egg-info/PKG-INFO
rtorrent_python.egg-info/SOURCES.txt
rtorrent_python.egg-info/dependency_links.txt
rtorrent_python.egg-info/top_level.txt