Metadata-Version: 1.0
Name: rtorrent-python
Version: 0.2.6
Summary: A simple rTorrent interface written in Python
Home-page: https://github.com/cjlucas/rtorrent-python
Author: Chris Lucas
Author-email: chris@chrisjlucas.com
License: MIT
Keywords: rtorrent p2p
Platform: UNKNOWN
Classifier: Development Status :: 4 - Beta
Classifier: Intended Audience :: Developers
Classifier: License :: OSI Approved :: MIT License
Classifier: Natural Language :: English
Classifier: Operating System :: OS Independent
Classifier: Programming Language :: Python
Classifier: Topic :: Communications :: File Sharing
Classifier: Topic :: Software Development :: Libraries :: Python Modules
